{
  "timestamp": "2025-06-13 14:30:03.639513",
  "input": {
    "course_topic": "Acids, Bases, and Salts",
    "difficulty_level": "Beginner",
    "num_modules": 6,
    "read_time_per_module": "5 minutes",
    "temperature": 0.65,
    "max_tokens": 1024,
    "top_k": 14,
    "top_p": 0.69
  },
  "output": {
    "conclusion": "By completing this course, you've gained a foundational understanding of acids, bases, and salts. You can now identify common examples, understand their properties, and appreciate their importance in everyday life and chemistry.",
    "courseTitle": "Acids, Bases, and Salts: A Beginner's Guide",
    "introduction": "Welcome to the world of acids, bases, and salts! This course will introduce you to these fundamental chemical concepts in a clear and easy-to-understand way. No prior chemistry knowledge is required.",
    "modules": [
      {
        "chapters": [
          {
            "chapterTitle": "What are Acids?",
            "description": "Introduction to acids: definition, sour taste, and examples like lemon juice and vinegar."
          },
          {
            "chapterTitle": "Common Acids",
            "description": "Brief overview of hydrochloric acid (HCl), sulfuric acid (H2SO4), and acetic acid (CH3COOH)."
          },
          {
            "chapterTitle": "Acidic Properties",
            "description": "Discusses properties of acids, such as reacting with metals and turning litmus paper red."
          }
        ],
        "moduleNumber": 1,
        "moduleTitle": "Introduction to Acids"
      },
      {
        "chapters": [
          {
            "chapterTitle": "What are Bases?",
            "description": "Introduction to bases: definition, bitter taste, slippery feel, and examples like soap and baking soda."
          },
          {
            "chapterTitle": "Common Bases",
            "description": "Brief overview of sodium hydroxide (NaOH), potassium hydroxide (KOH), and ammonia (NH3)."
          },
          {
            "chapterTitle": "Basic Properties",
            "description": "Discusses properties of bases, such as neutralizing acids and turning litmus paper blue."
          }
        ],
        "moduleNumber": 2,
        "moduleTitle": "Introduction to Bases"
      },
      {
        "chapters": [
          {
            "chapterTitle": "The pH Scale",
            "description": "Introduction to the pH scale: understanding acidity, neutrality, and alkalinity."
          },
          {
            "chapterTitle": "pH Indicators",
            "description": "Brief overview of pH indicators like litmus paper and universal indicator."
          },
          {
            "chapterTitle": "Measuring pH",
            "description": "Simple methods for measuring pH using indicators and pH meters."
          }
        ],
        "moduleNumber": 3,
        "moduleTitle": "Understanding pH"
      },
      {
        "chapters": [
          {
            "chapterTitle": "What are Salts?",
            "description": "Introduction to salts: definition as products of acid-base reactions."
          },
          {
            "chapterTitle": "Formation of Salts",
            "description": "Explaining how salts are formed through neutralization reactions."
          },
          {
            "chapterTitle": "Examples of Salts",
            "description": "Brief overview of common salts like sodium chloride (NaCl) and calcium carbonate (CaCO3)."
          }
        ],
        "moduleNumber": 4,
        "moduleTitle": "Introduction to Salts"
      },
      {
        "chapters": [
          {
            "chapterTitle": "Acid-Base Reactions",
            "description": "Understanding neutralization reactions between acids and bases."
          },
          {
            "chapterTitle": "Products of Neutralization",
            "description": "Explaining the formation of salt and water in neutralization reactions."
          },
          {
            "chapterTitle": "Balancing Equations",
            "description": "Simple examples of balancing chemical equations for acid-base reactions."
          }
        ],
        "moduleNumber": 5,
        "moduleTitle": "Acid-Base Reactions and Neutralization"
      },
      {
        "chapters": [
          {
            "chapterTitle": "Acids in Everyday Life",
            "description": "Examples of acids in food, cleaning products, and industrial processes."
          },
          {
            "chapterTitle": "Bases in Everyday Life",
            "description": "Examples of bases in cleaning products, medicines, and industrial processes."
          },
          {
            "chapterTitle": "Salts in Everyday Life",
            "description": "Examples of salts in food, medicine, and agriculture."
          }
        ],
        "moduleNumber": 6,
        "moduleTitle": "Applications of Acids, Bases, and Salts"
      }
    ]
  }
}